tileclipper/__init__.py
tileclipper/clipper.py
tileclipper-1.0.2.dist-info/LICENSE
tileclipper-1.0.2.dist-info/METADATA
tileclipper-1.0.2.dist-info/WHEEL
tileclipper-1.0.2.dist-info/top_level.txt
tileclipper-1.0.2.dist-info/RECORD
