Metadata-Version: 2.1
Name: tileclipper
Version: 1.0.2
Summary: The `TileClipper` package enables users to download map tiles within a specified bounding box from a tile server
Home-page: https://github.com/sijandh35/tileclipper
Author: Sijan Dhungana
Author-email: sijandhungana35@gmail.com
License: GPLv3
Keywords: map,tile,clip,download,tileclipper
Classifier: Development Status :: 3 - Alpha
Classifier: Intended Audience :: Developers
Classifier: Topic :: Scientific/Engineering :: GIS
Classifier: License :: OSI Approved :: GNU Affero General Public License v3
Classifier: Programming Language :: Python :: 3.8
License-File: LICENSE
Requires-Dist: requests ==2.31.0
Requires-Dist: pyproj ==3.6.1
Requires-Dist: tqdm ==4.66.1
Requires-Dist: boto3 ==1.24.54
